aliyunsdkhcs_mgw/__init__.py
aliyunsdkhcs_mgw/request/__init__.py
aliyunsdkhcs_mgw/request/v20171024/CheckImportDataAddressExRequest.py
aliyunsdkhcs_mgw/request/v20171024/CheckImportDataAddressRequest.py
aliyunsdkhcs_mgw/request/v20171024/CheckMigrationLicenseRequest.py
aliyunsdkhcs_mgw/request/v20171024/CheckRoleRequest.py
aliyunsdkhcs_mgw/request/v20171024/CreateDataAddressRequest.py
aliyunsdkhcs_mgw/request/v20171024/CreateImportJobExRequest.py
aliyunsdkhcs_mgw/request/v20171024/CreateImportJobRequest.py
aliyunsdkhcs_mgw/request/v20171024/CreateImportReportRequest.py
aliyunsdkhcs_mgw/request/v20171024/CreateJobRequest.py
aliyunsdkhcs_mgw/request/v20171024/CreateMigrationLicenseRequest.py
aliyunsdkhcs_mgw/request/v20171024/CreateMoverRequest.py
aliyunsdkhcs_mgw/request/v20171024/CreateOrderRequest.py
aliyunsdkhcs_mgw/request/v20171024/CreateRemoteRequest.py
aliyunsdkhcs_mgw/request/v20171024/CreateVirtualClusterRequest.py
aliyunsdkhcs_mgw/request/v20171024/DeleteDataAddressRequest.py
aliyunsdkhcs_mgw/request/v20171024/DeleteImportJobRequest.py
aliyunsdkhcs_mgw/request/v20171024/DeleteJobRequest.py
aliyunsdkhcs_mgw/request/v20171024/DeleteMoverRequest.py
aliyunsdkhcs_mgw/request/v20171024/DescribeBucketFoldersRequest.py
aliyunsdkhcs_mgw/request/v20171024/DescribeBucketsRequest.py
aliyunsdkhcs_mgw/request/v20171024/DescribeDataAddressesRequest.py
aliyunsdkhcs_mgw/request/v20171024/DescribeImportJobsRequest.py
aliyunsdkhcs_mgw/request/v20171024/DescribeImportReportRequest.py
aliyunsdkhcs_mgw/request/v20171024/DescribeJobsRequest.py
aliyunsdkhcs_mgw/request/v20171024/DescribeMigrationOrdersRequest.py
aliyunsdkhcs_mgw/request/v20171024/DescribeMoverAttributeRequest.py
aliyunsdkhcs_mgw/request/v20171024/DescribeMoversRequest.py
aliyunsdkhcs_mgw/request/v20171024/DescribeOfflineClusterRequest.py
aliyunsdkhcs_mgw/request/v20171024/DescribeRegionsRequest.py
aliyunsdkhcs_mgw/request/v20171024/DescribeRemotesRequest.py
aliyun_python_sdk_hcs_mgw-1.0.0.dist-info/LICENSE
aliyun_python_sdk_hcs_mgw-1.0.0.dist-info/METADATA
aliyun_python_sdk_hcs_mgw-1.0.0.dist-info/WHEEL
aliyun_python_sdk_hcs_mgw-1.0.0.dist-info/top_level.txt
aliyun_python_sdk_hcs_mgw-1.0.0.dist-info/RECORD
